{
  "products": [
    {
      "name": "WebClient",
      "services": [
        {
          "name": "WebClient",
          "description": "WebClient Service (stopped?)"
        }
      ],
      "pipes": [
        {
          "name": "DAV RPC SERVICE",
          "processes": []
        }
      ]
    },
    {
      "name": "Print Spooler",
      "services": [
        {
          "name": "Spooler",
          "description": "Print Spooler"
        }
      ],
      "pipes": [
        {
          "name": "spoolss",
          "processes": []
        }
      ]
    }
  ]
}
